aimaps/__init__.py
aimaps/aimaps.py
aimaps/common.py
aimaps-0.0.3.dist-info/LICENSE
aimaps-0.0.3.dist-info/METADATA
aimaps-0.0.3.dist-info/WHEEL
aimaps-0.0.3.dist-info/top_level.txt
aimaps-0.0.3.dist-info/RECORD
