Metadata-Version: 2.1
Name: aimaps
Version: 0.0.3
Summary: Python Boilerplate contains all the boilerplate you need to create a Python package.
Home-page: https://github.com/gisam/aimaps
Author: sam jackson
Author-email: sjackson608@gmail.com
License: MIT license
Keywords: aimaps
Classifier: Intended Audience :: Developers
Classifier: License :: OSI Approved :: MIT License
Classifier: Natural Language :: English
Classifier: Programming Language :: Python :: 3
Classifier: Programming Language :: Python :: 3.8
Classifier: Programming Language :: Python :: 3.9
Classifier: Programming Language :: Python :: 3.10
Classifier: Programming Language :: Python :: 3.11
Requires-Python: >=3.8
License-File: LICENSE
